odoo/addons/agresta_project_budget/.pre-commit-config.yaml
odoo/addons/agresta_project_budget/.pylintrc
odoo/addons/agresta_project_budget/__init__.py
odoo/addons/agresta_project_budget/__manifest__.py
odoo/addons/agresta_project_budget/data/scheduled_action.xml
odoo/addons/agresta_project_budget/data/security_groups.xml
odoo/addons/agresta_project_budget/models/__init__.py
odoo/addons/agresta_project_budget/models/project.py
odoo/addons/agresta_project_budget/models/project_task.py
odoo/addons/agresta_project_budget/models/project_task_update.py
odoo/addons/agresta_project_budget/models/project_update.py
odoo/addons/agresta_project_budget/security/ir.model.access.csv
odoo/addons/agresta_project_budget/views/menus.xml
odoo/addons/agresta_project_budget/views/project.xml
odoo/addons/agresta_project_budget/views/project_task.xml
odoo/addons/agresta_project_budget/views/project_update.xml
odoo_addon_agresta_project_budget-16.0.2.2.4.2.dist-info/METADATA
odoo_addon_agresta_project_budget-16.0.2.2.4.2.dist-info/WHEEL
odoo_addon_agresta_project_budget-16.0.2.2.4.2.dist-info/top_level.txt
odoo_addon_agresta_project_budget-16.0.2.2.4.2.dist-info/RECORD
